kvhosting
