Metadata-Version: 1.1
Name: kvhosting
Version: 1.0.4
Summary: Python client for keyvaluehosting.com
Home-page: https://github.com/shikolay/riak-python-client
Author: keyvaluehosting.com team
Author-email: info@keyvaluehosting.com
License: Apache 2
Platform: Platform Independent
Classifier: License :: OSI Approved :: Apache Software License
Classifier: Intended Audience :: Developers
Classifier: Operating System :: OS Independent
Classifier: Programming Language :: Python :: 2.7
Classifier: Programming Language :: Python :: 3.3
Classifier: Programming Language :: Python :: 3.4
Classifier: Programming Language :: Python :: 3.5
Classifier: Topic :: Database
Requires: six(>=1.8.0)
Requires: basho_erlastic(>= 2.1.1)
Requires: protobuf(>=2.4.1, <2.7.0)
